{"assets":[{"id":"image_0","w":960,"h":189,"u":"images/","p":"img_0.png"},{"id":"image_1","w":592,"h":325,"u":"images/","p":"img_1.png"}],"layers":[{"ddd":0,"ind":0,"ty":2,"nm":"按钮.png","cl":"png","td":1,"refId":"image_0","ks":{"o":{"k":100},"r":{"k":0},"p":{"k":[480,94.5,0]},"a":{"k":[480,94.5,0]},"s":{"k":[100,100,100]}},"ao":0,"ip":0,"op":36,"st":0,"bm":0,"sr":1},{"ddd":0,"ind":1,"ty":2,"nm":"激光.png","cl":"png","tt":1,"refId":"image_1","ks":{"o":{"k":[{"i":{"x":[0.833],"y":[0.833]},"o":{"x":[0.167],"y":[0.167]},"n":["0p833_0p833_0p167_0p167"],"t":0,"s":[30],"e":[100]},{"i":{"x":[0.833],"y":[0.833]},"o":{"x":[0.167],"y":[0.167]},"n":["0p833_0p833_0p167_0p167"],"t":10,"s":[100],"e":[100]},{"i":{"x":[0.833],"y":[0.833]},"o":{"x":[0.167],"y":[0.167]},"n":["0p833_0p833_0p167_0p167"],"t":25,"s":[100],"e":[30]},{"t":35}]},"r":{"k":0},"p":{"k":[{"i":{"x":0.667,"y":1},"o":{"x":0.333,"y":0},"n":"0p667_1_0p333_0","t":0,"s":[-178,94.5,0],"e":[1180,94.5,0],"to":[226.33332824707,0,0],"ti":[-226.33332824707,0,0]},{"t":35}]},"a":{"k":[296,162.5,0]},"s":{"k":[100,100,100]}},"ao":0,"ip":0,"op":36,"st":0,"bm":0,"sr":1},{"ddd":0,"ind":2,"ty":2,"nm":"按钮.png","cl":"png","refId":"image_0","ks":{"o":{"k":100},"r":{"k":0},"p":{"k":[480,94.5,0]},"a":{"k":[480,94.5,0]},"s":{"k":[100,100,100]}},"ao":0,"ip":0,"op":36,"st":0,"bm":0,"sr":1}],"v":"4.5.4","ddd":0,"ip":0,"op":36,"fr":30,"w":960,"h":189}